pibooth_qr_download.py
qr_filetransfer.py
pibooth_qr_download-0.1.2.dist-info/LICENSE
pibooth_qr_download-0.1.2.dist-info/METADATA
pibooth_qr_download-0.1.2.dist-info/WHEEL
pibooth_qr_download-0.1.2.dist-info/entry_points.txt
pibooth_qr_download-0.1.2.dist-info/top_level.txt
pibooth_qr_download-0.1.2.dist-info/RECORD
