Metadata-Version: 2.1
Name: pibooth-qr-download
Version: 0.1.2
Summary: Pibooth plugin to download picture via qr code.
Home-page: https://github.com/chilipp89/pibooth-qr-download
Author: P. Junietz
License: MIT
Keywords: Raspberry Pi,camera,photobooth,qrcode
Platform: unix
Platform: linux
Classifier: Development Status :: 5 - Production/Stable
Classifier: Environment :: Other Environment
Classifier: Intended Audience :: Developers
Classifier: Intended Audience :: End Users/Desktop
Classifier: License :: OSI Approved :: MIT License
Classifier: Operating System :: POSIX :: Linux
Classifier: Programming Language :: Python :: 3.6
Classifier: Programming Language :: Python :: 3.7
Classifier: Programming Language :: Python :: 3.8
Classifier: Programming Language :: Python :: 3.9
Classifier: Natural Language :: English
Classifier: Topic :: Multimedia :: Graphics :: Capture :: Digital Camera
Requires-Python: >=3.6
License-File: LICENSE
Requires-Dist: pibooth (>=2.0.0)
Requires-Dist: netifaces
